[
	{	
		"Key":"APACHE TOMCAT SERVER",
		"Value":
		{
			"m_Item1":"Java Web",
			"m_Item2":"Application Servers",
			"m_Item3":"1"
		}
	},
	{	
		"Key":"DENWER",
		"Value":
		{
			"m_Item1":"PHP Web",
			"m_Item2":"Application Servers",
			"m_Item3":"0"
		}
	},
	{	
		"Key":"WAMP",
		"Value":
		{
			"m_Item1":"PHP Web",
			"m_Item2":"Application Servers",
			"m_Item3":"1"
		}
	},
	{	
		"Key":"IBM WEBSPHERE APPLICATION SERVER",
		"Value":
		{
			"m_Item1":"Java Web",
			"m_Item2":"Application Servers",
			"m_Item3":"1"
		}
	},
	{	
		"Key":"API ECONOMY",
		"Value":
		{
			"m_Item1":"Other Web",
			"m_Item2":"Application Servers",
			"m_Item3":"1"
		}
	},
	{	
		"Key":"ORACLE WEBLOGIC APPLICATION SERVER",
		"Value":
		{
			"m_Item1":"Java Web",
			"m_Item2":"Application Servers",
			"m_Item3":"1"
		}
	},
	{	
		"Key":"MICROSOFT IIS",
		"Value":
		{
			"m_Item1":"Cpp Web",
			"m_Item2":"Application Servers",
			"m_Item3":"1"
		}
	},
	{	
		"Key":"IIS",
		"Value":
		{
			"m_Item1":"Cpp Web",
			"m_Item2":"Application Servers",
			"m_Item3":"0"
		}
	},
]